README.txt
setup.cfg
setup.py
docs/HISTORY.txt
docs/LICENSE.GPL
docs/LICENSE.txt
docs/MANUAL.txt
raptus/__init__.py
raptus.article.nesting.egg-info/PKG-INFO
raptus.article.nesting.egg-info/SOURCES.txt
raptus.article.nesting.egg-info/dependency_links.txt
raptus.article.nesting.egg-info/entry_points.txt
raptus.article.nesting.egg-info/namespace_packages.txt
raptus.article.nesting.egg-info/not-zip-safe
raptus.article.nesting.egg-info/requires.txt
raptus.article.nesting.egg-info/top_level.txt
raptus/article/__init__.py
raptus/article/nesting/__init__.py
raptus/article/nesting/articles.py
raptus/article/nesting/configure.zcml
raptus/article/nesting/extender.py
raptus/article/nesting/index.py
raptus/article/nesting/interfaces.py
raptus/article/nesting/setuphandlers.py
raptus/article/nesting/i18n/raptus.article-de.po
raptus/article/nesting/i18n/raptus.article-fr.po
raptus/article/nesting/i18n/raptus.article.pot
raptus/article/nesting/profiles/default/import_steps.xml
raptus/article/nesting/profiles/default/metadata.xml
raptus/article/nesting/profiles/default/raptus.article.nesting_install.txt
raptus/article/nesting/profiles/default/types.xml
raptus/article/nesting/profiles/default/types/Article.xml